{
    "items": [
        {
            "type": "tshirt",
            "gender": "female",
            "size": "large",
            "color": "pink",
            "image": "https://github.com/Nuung/all-about-javascript/blob/master/ShoppingGame/img/pink_t.png"
        },
        {
            "type": "pants",
            "gender": "male",
            "size": "large",
            "color": "blue",
            "image": "https://github.com/Nuung/all-about-javascript/blob/master/ShoppingGame/img/blue_p.png"
        },
        {
            "type": "pants",
            "gender": "female",
            "size": "small",
            "color": "yellow",
            "image": "https://github.com/Nuung/all-about-javascript/blob/master/ShoppingGame/img/yellow_p.png"
        },
        {
            "type": "shirt",
            "gender": "female",
            "size": "large",
            "color": "pink",
            "image": "https://github.com/Nuung/all-about-javascript/blob/master/ShoppingGame/img/pink_s.png"
        }
    ]
}